Workbook

Sheet Sales_Data
A1: Order ID | B1: Order Date | C1: Customer ID | D1: Product ID | E1: Region | F1: Segment | G1: Quantity | H1: Discount % | I1: Payment Method | J1: Order Status | K1: Unit Price | L1: Product | M1: Category | N1: Gross Sales | O1: Discount Amount | P1: Net Sales | Q1: Cost | R1: Profit | S1: Profit Margin %
A2: ORD0001 | B2: 45896 | C2: C008 | D2: P009 | E2: =IFERROR(VLOOKUP(C2,Customer_Master!$A$2:$E$16,4,FALSE),"") -> South | F2: =IFERROR(VLOOKUP(C2,Customer_Master!$A$2:$E$16,5,FALSE),"") -> Small Business | G2: 4 | H2: 0.15 | I2: COD | J2: Delivered | K2: =IFERROR(VLOOKUP(D2,Product_Master!$A$2:$F$13,5,FALSE),0) -> 1499 | L2: =IFERROR(VLOOKUP(D2,Product_Master!$A$2:$F$13,2,FALSE),"") -> Wireless Mouse | M2: =IFERROR(VLOOKUP(D2,Product_Master!$A$2:$F$13,3,FALSE),"") -> Accessories | N2: =G2*K2 -> 5996 | O2: =N2*H2 -> 899.4 | P2: =N2-O2 -> 5096.6 | Q2: =G2*IFERROR(VLOOKUP(D2,Product_Master!$A$2:$F$13,6,FALSE),0) -> 3000 | R2: =P2-Q2 -> 2096.6 | S2: =IFERROR(R2/P2,0) -> 0.41137229
A3: ORD0002 | B3: 45901 | C3: C003 | D3: P009 | E3: =IFERROR(VLOOKUP(C3,Customer_Master!$A$2:$E$16,4,FALSE),"") -> South | F3: =IFERROR(VLOOKUP(C3,Customer_Master!$A$2:$E$16,5,FALSE),"") -> Corporate | G3: 6 | H3: 0.15 | I3: Credit Card | J3: Delivered | K3: =IFERROR(VLOOKUP(D3,Product_Master!$A$2:$F$13,5,FALSE),0) -> 1499 | L3: =IFERROR(VLOOKUP(D3,Product_Master!$A$2:$F$13,2,FALSE),"") -> Wireless Mouse | M3: =IFERROR(VLOOKUP(D3,Product_Master!$A$2:$F$13,3,FALSE),"") -> Accessories | N3: =G3*K3 -> 8994 | O3: =N3*H3 -> 1349.1 | P3: =N3-O3 -> 7644.9 | Q3: =G3*IFERROR(VLOOKUP(D3,Product_Master!$A$2:$F$13,6,FALSE),0) -> 4500 | R3: =P3-Q3 -> 3144.9 | S3: =IFERROR(R3/P3,0) -> 0.41137229
A4: ORD0003 | B4: 45730 | C4: C008 | D4: P005 | E4: =IFERROR(VLOOKUP(C4,Customer_Master!$A$2:$E$16,4,FALSE),"") -> South | F4: =IFERROR(VLOOKUP(C4,Customer_Master!$A$2:$E$16,5,FALSE),"") -> Small Business | G4: 1 | H4: 0.15 | I4: UPI | J4: Returned | K4: =IFERROR(VLOOKUP(D4,Product_Master!$A$2:$F$13,5,FALSE),0) -> 28999 | L4: =IFERROR(VLOOKUP(D4,Product_Master!$A$2:$F$13,2,FALSE),"") -> Tablet Plus | M4: =IFERROR(VLOOKUP(D4,Product_Master!$A$2:$F$13,3,FALSE),"") -> Electronics | N4: =G4*K4 -> 28999 | O4: =N4*H4 -> 4349.85 | P4: =N4-O4 -> 24649.15 | Q4: =G4*IFERROR(VLOOKUP(D4,Product_Master!$A$2:$F$13,6,FALSE),0) -> 21500 | R4: =P4-Q4 -> 3149.15 | S4: =IFERROR(R4/P4,0) -> 0.12775897
A5: ORD0004 | B5: 45992 | C5: C007 | D5: P008 | E5: =IFERROR(VLOOKUP(C5,Customer_Master!$A$2:$E$16,4,FALSE),"") -> East | F5: =IFERROR(VLOOKUP(C5,Customer_Master!$A$2:$E$16,5,FALSE),"") -> Corporate | G5: 6 | H5: 0.15 | I5: Credit Card | J5: Returned | K5: =IFERROR(VLOOKUP(D5,Product_Master!$A$2:$F$13,5,FALSE),0) -> 3999 | L5: =IFERROR(VLOOKUP(D5,Product_Master!$A$2:$F$13,2,FALSE),"") -> Mechanical Keyboard | M5: =IFERROR(VLOOKUP(D5,Product_Master!$A$2:$F$13,3,FALSE),"") -> Accessories | N5: =G5*K5 -> 23994 | O5: =N5*H5 -> 3599.1 | P5: =N5-O5 -> 20394.9 | Q5: =G5*IFERROR(VLOOKUP(D5,Product_Master!$A$2:$F$13,6,FALSE),0) -> 14100 | R5: =P5-Q5 -> 6294.9 | S5: =IFERROR(R5/P5,0) -> 0.30865069
A6: ORD0005 | B6: 45690 | C6: C001 | D6: P009 | E6: =IFERROR(VLOOKUP(C6,Customer_Master!$A$2:$E$16,4,FALSE),"") -> North | F6: =IFERROR(VLOOKUP(C6,Customer_Master!$A$2:$E$16,5,FALSE),"") -> Corporate | G6: 1 | H6: 0 | I6: Credit Card | J6: Delivered | K6: =IFERROR(VLOOKUP(D6,Product_Master!$A$2:$F$13,5,FALSE),0) -> 1499 | L6: =IFERROR(VLOOKUP(D6,Product_Master!$A$2:$F$13,2,FALSE),"") -> Wireless Mouse | M6: =IFERROR(VLOOKUP(D6,Product_Master!$A$2:$F$13,3,FALSE),"") -> Accessories | N6: =G6*K6 -> 1499 | O6: =N6*H6 -> 0 | P6: =N6-O6 -> 1499 | Q6: =G6*IFERROR(VLOOKUP(D6,Product_Master!$A$2:$F$13,6,FALSE),0) -> 750 | R6: =P6-Q6 -> 749 | S6: =IFERROR(R6/P6,0) -> 0.49966644
A7: ORD0006 | B7: 45895 | C7: C010 | D7: P001 | E7: =IFERROR(VLOOKUP(C7,Customer_Master!$A$2:$E$16,4,FALSE),"") -> North | F7: =IFERROR(VLOOKUP(C7,Customer_Master!$A$2:$E$16,5,FALSE),"") -> Consumer | G7: 3 | H7: 0.1 | I7: COD | J7: Delivered | K7: =IFERROR(VLOOKUP(D7,Product_Master!$A$2:$F$13,5,FALSE),0) -> 74999 | L7: =IFERROR(VLOOKUP(D7,Product_Master!$A$2:$F$13,2,FALSE),"") -> Laptop Pro 14 | M7: =IFERROR(VLOOKUP(D7,Product_Master!$A$2:$F$13,3,FALSE),"") -> Electronics | N7: =G7*K7 -> 224997 | O7: =N7*H7 -> 22499.7 | P7: =N7-O7 -> 202497.3 | Q7: =G7*IFERROR(VLOOKUP(D7,Product_Master!$A$2:$F$13,6,FALSE),0) -> 175500 | R7: =P7-Q7 -> 26997.3 | S7: =IFERROR(R7/P7,0) -> 0.13332178
A8: ORD0007 | B8: 45985 | C8: C009 | D8: P004 | E8: =IFERROR(VLOOKUP(C8,Customer_Master!$A$2:$E$16,4,FALSE),"") -> West | F8: =IFERROR(VLOOKUP(C8,Customer_Master!$A$2:$E$16,5,FALSE),"") -> Corporate | G8: 3 | H8: 0.1 | I8: UPI | J8: Delivered | K8: =IFERROR(VLOOKUP(D8,Product_Master!$A$2:$F$13,5,FALSE),0) -> 24999 | L8: =IFERROR(VLOOKUP(D8,Product_Master!$A$2:$F$13,2,FALSE),"") -> Smartphone Lite | M8: =IFERROR(VLOOKUP(D8,Product_Master!$A$2:$F$13,3,FALSE),"") -> Electronics | N8: =G8*K8 -> 74997 | O8: =N8*H8 -> 7499.7 | P8: =N8-O8 -> 67497.3 | Q8: =G8*IFERROR(VLOOKUP(D8,Product_Master!$A$2:$F$13,6,FALSE),0) -> 55500 | R8: =P8-Q8 -> 11997.3 | S8: =IFERROR(R8/P8,0) -> 0.17774489
A9: ORD0008 | B9: 45800 | C9: C008 | D9: P011 | E9: =IFERROR(VLOOKUP(C9,Customer_Master!$A$2:$E$16,4,FALSE),"") -> South | F9: =IFERROR(VLOOKUP(C9,Customer_Master!$A$2:$E$16,5,FALSE),"") -> Small Business | G9: 4 | H9: 0.15 | I9: UPI | J9: Delivered | K9: =IFERROR(VLOOKUP(D9,Product_Master!$A$2:$F$13,5,FALSE),0) -> 8999 | L9: =IFERROR(VLOOKUP(D9,Product_Master!$A$2:$F$13,2,FALSE),"") -> Office Chair | M9: =IFERROR(VLOOKUP(D9,Product_Master!$A$2:$F$13,3,FALSE),"") -> Furniture | N9: =G9*K9 -> 35996 | O9: =N9*H9 -> 5399.4 | P9: =N9-O9 -> 30596.6 | Q9: =G9*IFERROR(VLOOKUP(D9,Product_Master!$A$2:$F$13,6,FALSE),0) -> 24400 | R9: =P9-Q9 -> 6196.6 | S9: =IFERROR(R9/P9,0) -> 0.20252577
A10: ORD0009 | B10: 45920 | C10: C006 | D10: P004 | E10: =IFERROR(VLOOKUP(C10,Customer_Master!$A$2:$E$16,4,FALSE),"") -> North | F10: =IFERROR(VLOOKUP(C10,Customer_Master!$A$2:$E$16,5,FALSE),"") -> Consumer | G10: 3 | H10: 0 | I10: UPI | J10: Returned | K10: =IFERROR(VLOOKUP(D10,Product_Master!$A$2:$F$13,5,FALSE),0) -> 24999 | L10: =IFERROR(VLOOKUP(D10,Product_Master!$A$2:$F$13,2,FALSE),"") -> Smartphone Lite | M10: =IFERROR(VLOOKUP(D10,Product_Master!$A$2:$F$13,3,FALSE),"") -> Electronics | N10: =G10*K10 -> 74997 | O10: =N10*H10 -> 0 | P10: =N10-O10 -> 74997 | Q10: =G10*IFERROR(VLOOKUP(D10,Product_Master!$A$2:$F$13,6,FALSE),0) -> 55500 | R10: =P10-Q10 -> 19497 | S10: =IFERROR(R10/P10,0) -> 0.2599704
A11: ORD0010 | B11: 45863 | C11: C013 | D11: P002 | E11: =IFERROR(VLOOKUP(C11,Customer_Master!$A$2:$E$16,4,FALSE),"") -> West | F11: =IFERROR(VLOOKUP(C11,Customer_Master!$A$2:$E$16,5,FALSE),"") -> Corporate | G11: 1 | H11: 0.05 | I11: Net Banking | J11: Delivered | K11: =IFERROR(VLOOKUP(D11,Product_Master!$A$2:$F$13,5,FALSE),0) -> 62999 | L11: =IFERROR(VLOOKUP(D11,Product_Master!$A$2:$F$13,2,FALSE),"") -> Laptop Air 13 | M11: =IFERROR(VLOOKUP(D11,Product_Master!$A$2:$F$13,3,FALSE),"") -> Electronics | N11: =G11*K11 -> 62999 | O11: =N11*H11 -> 3149.95 | P11: =N11-O11 -> 59849.05 | Q11: =G11*IFERROR(VLOOKUP(D11,Product_Master!$A$2:$F$13,6,FALSE),0) -> 49000 | R11: =P11-Q11 -> 10849.05 | S11: =IFERROR(R11/P11,0) -> 0.18127355
A12: ORD0011 | B12: 45658 | C12: C001 | D12: P011 | E12: =IFERROR(VLOOKUP(C12,Customer_Master!$A$2:$E$16,4,FALSE),"") -> North | F12: =IFERROR(VLOOKUP(C12,Customer_Master!$A$2:$E$16,5,FALSE),"") -> Corporate | G12: 2 | H12: 0.05 | I12: UPI | J12: Delivered | K12: =IFERROR(VLOOKUP(D12,Product_Master!$A$2:$F$13,5,FALSE),0) -> 8999 | L12: =IFERROR(VLOOKUP(D12,Product_Master!$A$2:$F$13,2,FALSE),"") -> Office Chair | M12: =IFERROR(VLOOKUP(D12,Product_Master!$A$2:$F$13,3,FALSE),"") -> Furniture | N12: =G12*K12 -> 17998 | O12: =N12*H12 -> 899.9 | P12: =N12-O12 -> 17098.1 | Q12: =G12*IFERROR(VLOOKUP(D12,Product_Master!$A$2:$F$13,6,FALSE),0) -> 12200 | R12: =P12-Q12 -> 4898.1 | S12: =IFERROR(R12/P12,0) -> 0.28647043
A13: ORD0012 | B13: 45861 | C13: C007 | D13: P012 | E13: =IFERROR(VLOOKUP(C13,Customer_Master!$A$2:$E$16,4,FALSE),"") -> East | F13: =IFERROR(VLOOKUP(C13,Customer_Master!$A$2:$E$16,5,FALSE),"") -> Corporate | G13: 4 | H13: 0 | I13: COD | J13: Delivered | K13: =IFERROR(VLOOKUP(D13,Product_Master!$A$2:$F$13,5,FALSE),0) -> 6999 | L13: =IFERROR(VLOOKUP(D13,Product_Master!$A$2:$F$13,2,FALSE),"") -> Study Desk | M13: =IFERROR(VLOOKUP(D13,Product_Master!$A$2:$F$13,3,FALSE),"") -> Furniture | N13: =G13*K13 -> 27996 | O13: =N13*H13 -> 0 | P13: =N13-O13 -> 27996 | Q13: =G13*IFERROR(VLOOKUP(D13,Product_Master!$A$2:$F$13,6,FALSE),0) -> 18000 | R13: =P13-Q13 -> 9996 | S13: =IFERROR(R13/P13,0) -> 0.35705101
... A301: ORD0300 | B301: 45752 | C301: C004 | D301: P011 | E301: =IFERROR(VLOOKUP(C301,Customer_Master!$A$2:$E$16,4,FALSE),"") -> South | F301: =IFERROR(VLOOKUP(C301,Customer_Master!$A$2:$E$16,5,FALSE),"") -> Consumer | G301: 1 | H301: 0.1 | I301: COD | J301: Delivered | K301: =IFERROR(VLOOKUP(D301,Product_Master!$A$2:$F$13,5,FALSE),0) -> 8999 | L301: =IFERROR(VLOOKUP(D301,Product_Master!$A$2:$F$13,2,FALSE),"") -> Office Chair | M301: =IFERROR(VLOOKUP(D301,Product_Master!$A$2:$F$13,3,FALSE),"") -> Furniture | N301: =G301*K301 -> 8999 | O301: =N301*H301 -> 899.9 | P301: =N301-O301 -> 8099.1 | Q301: =G301*IFERROR(VLOOKUP(D301,Product_Master!$A$2:$F$13,6,FALSE),0) -> 6100 | R301: =P301-Q301 -> 1999.1 | S301: =IFERROR(R301/P301,0) -> 0.24682989

Sheet Product_Master
A1: Product ID | B1: Product Name | C1: Category | D1: Subcategory | E1: Unit Price | F1: Cost Price
A2: P001 | B2: Laptop Pro 14 | C2: Electronics | D2: Computers | E2: 74999 | F2: 58500
A3: P002 | B3: Laptop Air 13 | C3: Electronics | D3: Computers | E3: 62999 | F3: 49000
A4: P003 | B4: Smartphone X | C4: Electronics | D4: Mobiles | E4: 39999 | F4: 30000
A5: P004 | B5: Smartphone Lite | C5: Electronics | D5: Mobiles | E5: 24999 | F5: 18500
A6: P005 | B6: Tablet Plus | C6: Electronics | D6: Tablets | E6: 28999 | F6: 21500
A7: P006 | B7: Wireless Headphones | C7: Electronics | D7: Audio | E7: 4999 | F7: 2900
A8: P007 | B8: Bluetooth Speaker | C8: Electronics | D8: Audio | E8: 3499 | F8: 2050
A9: P008 | B9: Mechanical Keyboard | C9: Accessories | D9: Computer Accessories | E9: 3999 | F9: 2350
A10: P009 | B10: Wireless Mouse | C10: Accessories | D10: Computer Accessories | E10: 1499 | F10: 750
A11: P010 | B11: USB-C Hub | C11: Accessories | D11: Computer Accessories | E11: 2499 | F11: 1450
A12: P011 | B12: Office Chair | C12: Furniture | D12: Office | E12: 8999 | F12: 6100
A13: P012 | B13: Study Desk | C13: Furniture | D13: Office | E13: 6999 | F13: 4500

Sheet Customer_Master
A1: Customer ID | B1: Customer Name | C1: City | D1: Region | E1: Segment
A2: C001 | B2: Aarav Sharma | C2: Delhi | D2: North | E2: Corporate
A3: C002 | B3: Diya Mehta | C3: Mumbai | D3: West | E3: Consumer
A4: C003 | B4: Kabir Rao | C4: Bengaluru | D4: South | E4: Corporate
A5: C004 | B5: Anaya Singh | C5: Hyderabad | D5: South | E5: Consumer
A6: C005 | B6: Vivaan Shah | C6: Pune | D6: West | E6: Small Business
A7: C006 | B7: Ishita Jain | C7: Jaipur | D7: North | E7: Consumer
A8: C007 | B8: Arjun Das | C8: Kolkata | D8: East | E8: Corporate
A9: C008 | B9: Myra Nair | C9: Chennai | D9: South | E9: Small Business
A10: C009 | B10: Rohan Patel | C10: Ahmedabad | D10: West | E10: Corporate
A11: C010 | B11: Sara Khan | C11: Lucknow | D11: North | E11: Consumer
A12: C011 | B12: Advik Verma | C12: Bhopal | D12: Central | E12: Small Business
... A16: C015 | B16: Neil Sen | C16: Bhubaneswar | D16: East | E16: Small Business

Sheet Pivot_Analysis
A1: PIVOT-STYLE BUSINESS ANALYSIS
A2: Summary tables for PivotTable practice and dashboard reporting.
A4: Region | B4: Net Sales | C4: Profit | D4: Orders | F4: Category | G4: Net Sales | H4: Profit | I4: Quantity | K4: Segment | L4: Net Sales | M4: Orders
A5: North | B5: =SUMIF(Sales_Data!E$2:E$301,A5,Sales_Data!P$2:P$301) -> 4586100.8 | C5: =SUMIF(Sales_Data!E$2:E$301,A5,Sales_Data!R$2:R$301) -> 871800.85 | D5: =COUNTIF(Sales_Data!E$2:E$301,A5) -> 64 | F5: Electronics | G5: =SUMIF(Sales_Data!M$2:M$301,F5,Sales_Data!P$2:P$301) -> 16415649 | H5: =SUMIF(Sales_Data!M$2:M$301,F5,Sales_Data!R$2:R$301) -> 3036598.8 | I5: =SUMIF(Sales_Data!M$2:M$301,F5,Sales_Data!G$2:G$301) -> 567 | K5: Consumer | L5: =SUMIF(Sales_Data!F$2:F$301,K5,Sales_Data!P$2:P$301) -> 6951308 | M5: =COUNTIF(Sales_Data!F$2:F$301,K5) -> 111
A6: South | B6: =SUMIF(Sales_Data!E$2:E$301,A6,Sales_Data!P$2:P$301) -> 3068657.3 | C6: =SUMIF(Sales_Data!E$2:E$301,A6,Sales_Data!R$2:R$301) -> 545257.25 | D6: =COUNTIF(Sales_Data!E$2:E$301,A6) -> 55 | F6: Accessories | G6: =SUMIF(Sales_Data!M$2:M$301,F6,Sales_Data!P$2:P$301) -> 761970.45 | H6: =SUMIF(Sales_Data!M$2:M$301,F6,Sales_Data!R$2:R$301) -> 294120.45 | I6: =SUMIF(Sales_Data!M$2:M$301,F6,Sales_Data!G$2:G$301) -> 303 | K6: Corporate | L6: =SUMIF(Sales_Data!F$2:F$301,K6,Sales_Data!P$2:P$301) -> 6050606.4 | M6: =COUNTIF(Sales_Data!F$2:F$301,K6) -> 103
A7: East | B7: =SUMIF(Sales_Data!E$2:E$301,A7,Sales_Data!P$2:P$301) -> 3871319.9 | C7: =SUMIF(Sales_Data!E$2:E$301,A7,Sales_Data!R$2:R$301) -> 847919.85 | D7: =COUNTIF(Sales_Data!E$2:E$301,A7) -> 64 | F7: Furniture | G7: =SUMIF(Sales_Data!M$2:M$301,F7,Sales_Data!P$2:P$301) -> 1384584 | H7: =SUMIF(Sales_Data!M$2:M$301,F7,Sales_Data!R$2:R$301) -> 393183.95 | I7: =SUMIF(Sales_Data!M$2:M$301,F7,Sales_Data!G$2:G$301) -> 178 | K7: Small Business | L7: =SUMIF(Sales_Data!F$2:F$301,K7,Sales_Data!P$2:P$301) -> 5560288.9 | M7: =COUNTIF(Sales_Data!F$2:F$301,K7) -> 86
A8: West | B8: =SUMIF(Sales_Data!E$2:E$301,A8,Sales_Data!P$2:P$301) -> 4961082.6 | C8: =SUMIF(Sales_Data!E$2:E$301,A8,Sales_Data!R$2:R$301) -> 1044682.6 | D8: =COUNTIF(Sales_Data!E$2:E$301,A8) -> 79
A9: Central | B9: =SUMIF(Sales_Data!E$2:E$301,A9,Sales_Data!P$2:P$301) -> 2075042.6 | C9: =SUMIF(Sales_Data!E$2:E$301,A9,Sales_Data!R$2:R$301) -> 414242.65 | D9: =COUNTIF(Sales_Data!E$2:E$301,A9) -> 38
A12: Month | B12: Net Sales | C12: Profit
A13: Jan | B13: =SUMIFS(Sales_Data!P$2:P$301,Sales_Data!B$2:B$301,">="&DATE(2025,1,1),Sales_Data!B$2:B$301,"<"&DATE(2025,2,1)) -> 1427704.6 | C13: =SUMIFS(Sales_Data!R$2:R$301,Sales_Data!B$2:B$301,">="&DATE(2025,1,1),Sales_Data!B$2:B$301,"<"&DATE(2025,2,1)) -> 289204.65
A14: Feb | B14: =SUMIFS(Sales_Data!P$2:P$301,Sales_Data!B$2:B$301,">="&DATE(2025,2,1),Sales_Data!B$2:B$301,"<"&DATE(2025,3,1)) -> 1673143.8 | C14: =SUMIFS(Sales_Data!R$2:R$301,Sales_Data!B$2:B$301,">="&DATE(2025,2,1),Sales_Data!B$2:B$301,"<"&DATE(2025,3,1)) -> 347043.75
A15: Mar | B15: =SUMIFS(Sales_Data!P$2:P$301,Sales_Data!B$2:B$301,">="&DATE(2025,3,1),Sales_Data!B$2:B$301,"<"&DATE(2025,4,1)) -> 923951.85 | C15: =SUMIFS(Sales_Data!R$2:R$301,Sales_Data!B$2:B$301,">="&DATE(2025,3,1),Sales_Data!B$2:B$301,"<"&DATE(2025,4,1)) -> 186251.85
A16: Apr | B16: =SUMIFS(Sales_Data!P$2:P$301,Sales_Data!B$2:B$301,">="&DATE(2025,4,1),Sales_Data!B$2:B$301,"<"&DATE(2025,5,1)) -> 1419704.2 | C16: =SUMIFS(Sales_Data!R$2:R$301,Sales_Data!B$2:B$301,">="&DATE(2025,4,1),Sales_Data!B$2:B$301,"<"&DATE(2025,5,1)) -> 257504.2
A17: May | B17: =SUMIFS(Sales_Data!P$2:P$301,Sales_Data!B$2:B$301,">="&DATE(2025,5,1),Sales_Data!B$2:B$301,"<"&DATE(2025,6,1)) -> 1258862.5 | C17: =SUMIFS(Sales_Data!R$2:R$301,Sales_Data!B$2:B$301,">="&DATE(2025,5,1),Sales_Data!B$2:B$301,"<"&DATE(2025,6,1)) -> 288812.55
A18: Jun | B18: =SUMIFS(Sales_Data!P$2:P$301,Sales_Data!B$2:B$301,">="&DATE(2025,6,1),Sales_Data!B$2:B$301,"<"&DATE(2025,7,1)) -> 2624967.5 | C18: =SUMIFS(Sales_Data!R$2:R$301,Sales_Data!B$2:B$301,">="&DATE(2025,6,1),Sales_Data!B$2:B$301,"<"&DATE(2025,7,1)) -> 512717.55
A19: Jul | B19: =SUMIFS(Sales_Data!P$2:P$301,Sales_Data!B$2:B$301,">="&DATE(2025,7,1),Sales_Data!B$2:B$301,"<"&DATE(2025,8,1)) -> 1516865.5 | C19: =SUMIFS(Sales_Data!R$2:R$301,Sales_Data!B$2:B$301,">="&DATE(2025,7,1),Sales_Data!B$2:B$301,"<"&DATE(2025,8,1)) -> 291165.5
A20: Aug | B20: =SUMIFS(Sales_Data!P$2:P$301,Sales_Data!B$2:B$301,">="&DATE(2025,8,1),Sales_Data!B$2:B$301,"<"&DATE(2025,9,1)) -> 2355041.9 | C20: =SUMIFS(Sales_Data!R$2:R$301,Sales_Data!B$2:B$301,">="&DATE(2025,8,1),Sales_Data!B$2:B$301,"<"&DATE(2025,9,1)) -> 493391.85
A21: Sep | B21: =SUMIFS(Sales_Data!P$2:P$301,Sales_Data!B$2:B$301,">="&DATE(2025,9,1),Sales_Data!B$2:B$301,"<"&DATE(2025,10,1)) -> 1312882.1 | C21: =SUMIFS(Sales_Data!R$2:R$301,Sales_Data!B$2:B$301,">="&DATE(2025,9,1),Sales_Data!B$2:B$301,"<"&DATE(2025,10,1)) -> 215832.05
A22: Oct | B22: =SUMIFS(Sales_Data!P$2:P$301,Sales_Data!B$2:B$301,">="&DATE(2025,10,1),Sales_Data!B$2:B$301,"<"&DATE(2025,11,1)) -> 2031338.2 | C22: =SUMIFS(Sales_Data!R$2:R$301,Sales_Data!B$2:B$301,">="&DATE(2025,10,1),Sales_Data!B$2:B$301,"<"&DATE(2025,11,1)) -> 407388.2
A23: Nov | B23: =SUMIFS(Sales_Data!P$2:P$301,Sales_Data!B$2:B$301,">="&DATE(2025,11,1),Sales_Data!B$2:B$301,"<"&DATE(2025,12,1)) -> 583257.8 | C23: =SUMIFS(Sales_Data!R$2:R$301,Sales_Data!B$2:B$301,">="&DATE(2025,11,1),Sales_Data!B$2:B$301,"<"&DATE(2025,12,1)) -> 115957.8
A24: Dec | B24: =SUMIFS(Sales_Data!P$2:P$301,Sales_Data!B$2:B$301,">="&DATE(2025,12,1),Sales_Data!B$2:B$301,"<"&DATE(2026,1,1)) -> 1434483.2 | C24: =SUMIFS(Sales_Data!R$2:R$301,Sales_Data!B$2:B$301,">="&DATE(2025,12,1),Sales_Data!B$2:B$301,"<"&DATE(2026,1,1)) -> 318633.25

Sheet Dashboard
A1: RETAIL SALES & PROFIT ANALYTICS
A2: Excel portfolio project • VLOOKUP • SUMIFS • Pivot-style analysis • KPI dashboard
A4: TOTAL ORDERS | D4: NET SALES | G4: TOTAL PROFIT | J4: PROFIT MARGIN
A5: =COUNTA(Sales_Data!A2:A301) -> 300 | D5: =SUM(Sales_Data!P2:P301) -> 18562203 | G5: =SUM(Sales_Data!R2:R301) -> 3723903.2 | J5: =IFERROR(G5/D5,0) -> 0.20061752
A9: Region | B9: Net Sales | D9: Category | E9: Net Sales | G9: Month | H9: Net Sales | I9: Profit | K9: Payment Method | L9: Orders
A10: =Pivot_Analysis!A5 -> North | B10: =Pivot_Analysis!B5 -> 4586100.8 | D10: =Pivot_Analysis!F5 -> Electronics | E10: =Pivot_Analysis!G5 -> 16415649 | G10: =Pivot_Analysis!A13 -> Jan | H10: =Pivot_Analysis!B13 -> 1427704.6 | I10: =Pivot_Analysis!C13 -> 289204.65 | K10: UPI | L10: =COUNTIF(Sales_Data!I$2:I$301,K10) -> 62
A11: =Pivot_Analysis!A6 -> South | B11: =Pivot_Analysis!B6 -> 3068657.3 | D11: =Pivot_Analysis!F6 -> Accessories | E11: =Pivot_Analysis!G6 -> 761970.45 | G11: =Pivot_Analysis!A14 -> Feb | H11: =Pivot_Analysis!B14 -> 1673143.8 | I11: =Pivot_Analysis!C14 -> 347043.75 | K11: Credit Card | L11: =COUNTIF(Sales_Data!I$2:I$301,K11) -> 64
A12: =Pivot_Analysis!A7 -> East | B12: =Pivot_Analysis!B7 -> 3871319.9 | D12: =Pivot_Analysis!F7 -> Furniture | E12: =Pivot_Analysis!G7 -> 1384584 | G12: =Pivot_Analysis!A15 -> Mar | H12: =Pivot_Analysis!B15 -> 923951.85 | I12: =Pivot_Analysis!C15 -> 186251.85 | K12: Debit Card | L12: =COUNTIF(Sales_Data!I$2:I$301,K12) -> 58
A13: =Pivot_Analysis!A8 -> West | B13: =Pivot_Analysis!B8 -> 4961082.6 | G13: =Pivot_Analysis!A16 -> Apr | H13: =Pivot_Analysis!B16 -> 1419704.2 | I13: =Pivot_Analysis!C16 -> 257504.2 | K13: Net Banking | L13: =COUNTIF(Sales_Data!I$2:I$301,K13) -> 51
A14: =Pivot_Analysis!A9 -> Central | B14: =Pivot_Analysis!B9 -> 2075042.6 | G14: =Pivot_Analysis!A17 -> May | H14: =Pivot_Analysis!B17 -> 1258862.5 | I14: =Pivot_Analysis!C17 -> 288812.55 | K14: COD | L14: =COUNTIF(Sales_Data!I$2:I$301,K14) -> 65
G15: =Pivot_Analysis!A18 -> Jun | H15: =Pivot_Analysis!B18 -> 2624967.5 | I15: =Pivot_Analysis!C18 -> 512717.55
G16: =Pivot_Analysis!A19 -> Jul | H16: =Pivot_Analysis!B19 -> 1516865.5 | I16: =Pivot_Analysis!C19 -> 291165.5
G17: =Pivot_Analysis!A20 -> Aug | H17: =Pivot_Analysis!B20 -> 2355041.9 | I17: =Pivot_Analysis!C20 -> 493391.85
G18: =Pivot_Analysis!A21 -> Sep | H18: =Pivot_Analysis!B21 -> 1312882.1 | I18: =Pivot_Analysis!C21 -> 215832.05
G19: =Pivot_Analysis!A22 -> Oct | H19: =Pivot_Analysis!B22 -> 2031338.2 | I19: =Pivot_Analysis!C22 -> 407388.2
G20: =Pivot_Analysis!A23 -> Nov | H20: =Pivot_Analysis!B23 -> 583257.8 | I20: =Pivot_Analysis!C23 -> 115957.8
G21: =Pivot_Analysis!A24 -> Dec | H21: =Pivot_Analysis!B24 -> 1434483.2 | I21: =Pivot_Analysis!C24 -> 318633.25

Sheet Instructions
A1: Excel Portfolio Project - Guide
A2: 1. Sales_Data contains 300 realistic orders and formula-driven lookup columns.
A3: 2. Product_Master and Customer_Master are lookup tables.
A4: 3. Pivot_Analysis contains business summaries by region, category, segment and month.
A5: 4. Dashboard contains KPI cards and four chart types: horizontal bar, line, doughnut and payment-method bar.
A6: 5. Practice creating real PivotTables from Sales_Data: Region vs Net Sales, Category vs Profit, Segment vs Orders, Month vs Net Sales.
A7: 6. Formula skills: VLOOKUP, IFERROR, SUM, SUMIF, SUMIFS, COUNTIF, COUNTA, AVERAGE, IF.
